[
  {
    "stock_id": "ADANIENT",
    "mode": "per_stock",
    "generated_at": "2026-03-27T15:35:07.982862Z",
    "report_path": "/app/backend/models/model_store/feature_ablation/ADANIENT_per_stock_feature_ablation_report.json",
    "configured_channels": [
      "price",
      "index",
      "usd_inr",
      "revenue",
      "profit"
    ],
    "transform_name": "stft",
    "entries": [
      {
        "label": "baseline",
        "channels": [
          "price",
          "index",
          "usd_inr",
          "revenue",
          "profit"
        ],
        "removed_channel": null,
        "mse": 111500.8828125,
        "rmse": 333.91747904609605,
        "mae": 236.63327026367188,
        "mape": 10.48896312713623,
        "directional_accuracy": 53.333333333333336,
        "delta_mse": null,
        "delta_rmse": null,
        "delta_mae": null,
        "delta_mape": null,
        "delta_directional_accuracy": null
      },
      {
        "label": "minus_price",
        "channels": [
          "index",
          "usd_inr",
          "revenue",
          "profit"
        ],
        "removed_channel": "price",
        "mse": 925360.75,
        "rmse": 961.9567297960964,
        "mae": 795.220458984375,
        "mape": 32.57878494262695,
        "directional_accuracy": 57.49999999999999,
        "delta_mse": 813859.8671875,
        "delta_rmse": 628.0392507500003,
        "delta_mae": 558.5871887207031,
        "delta_mape": 22.089821815490723,
        "delta_directional_accuracy": 4.166666666666657
      },
      {
        "label": "minus_index",
        "channels": [
          "price",
          "usd_inr",
          "revenue",
          "profit"
        ],
        "removed_channel": "index",
        "mse": 777457.0625,
        "rmse": 881.735256468743,
        "mae": 842.9102783203125,
        "mape": 35.275733947753906,
        "directional_accuracy": 55.41666666666667,
        "delta_mse": 665956.1796875,
        "delta_rmse": 547.8177774226469,
        "delta_mae": 606.2770080566406,
        "delta_mape": 24.786770820617676,
        "delta_directional_accuracy": 2.0833333333333357
      },
      {
        "label": "minus_usd_inr",
        "channels": [
          "price",
          "index",
          "revenue",
          "profit"
        ],
        "removed_channel": "usd_inr",
        "mse": 433447.65625,
        "rmse": 658.3674173666252,
        "mae": 626.3062744140625,
        "mape": 26.184326171875,
        "directional_accuracy": 55.00000000000001,
        "delta_mse": 321946.7734375,
        "delta_rmse": 324.44993832052916,
        "delta_mae": 389.6730041503906,
        "delta_mape": 15.69536304473877,
        "delta_directional_accuracy": 1.6666666666666714
      },
      {
        "label": "minus_revenue",
        "channels": [
          "price",
          "index",
          "usd_inr",
          "profit"
        ],
        "removed_channel": "revenue",
        "mse": 56405.2265625,
        "rmse": 237.49784538496343,
        "mae": 199.46255493164062,
        "mape": 8.969630241394043,
        "directional_accuracy": 47.5,
        "delta_mse": -55095.65625,
        "delta_rmse": -96.41963366113262,
        "delta_mae": -37.17071533203125,
        "delta_mape": -1.5193328857421875,
        "delta_directional_accuracy": -5.833333333333336
      },
      {
        "label": "minus_profit",
        "channels": [
          "price",
          "index",
          "usd_inr",
          "revenue"
        ],
        "removed_channel": "profit",
        "mse": 341736.0625,
        "rmse": 584.5819553321844,
        "mae": 536.0156860351562,
        "mape": 23.760786056518555,
        "directional_accuracy": 44.166666666666664,
        "delta_mse": 230235.1796875,
        "delta_rmse": 250.66447628608836,
        "delta_mae": 299.3824157714844,
        "delta_mape": 13.271822929382324,
        "delta_directional_accuracy": -9.166666666666671
      }
    ]
  },
  {
    "stock_id": "ADANIENT",
    "mode": "unified_with_embeddings",
    "generated_at": "2026-03-27T16:49:54.666766Z",
    "report_path": "/app/backend/models/model_store/feature_ablation/ADANIENT_unified_with_embeddings_feature_ablation_report.json",
    "configured_channels": [
      "price",
      "index",
      "usd_inr",
      "revenue",
      "profit"
    ],
    "transform_name": "stft",
    "entries": [
      {
        "label": "baseline",
        "channels": [
          "price",
          "index",
          "usd_inr",
          "revenue",
          "profit"
        ],
        "removed_channel": null,
        "mse": 2138769.25,
        "rmse": 1462.4531616431345,
        "mae": 1415.1619873046875,
        "mape": 61.742164611816406,
        "directional_accuracy": 44.537815126050425,
        "delta_mse": null,
        "delta_rmse": null,
        "delta_mae": null,
        "delta_mape": null,
        "delta_directional_accuracy": null
      },
      {
        "label": "minus_price",
        "channels": [
          "index",
          "usd_inr",
          "revenue",
          "profit"
        ],
        "removed_channel": "price",
        "mse": 3249964.75,
        "rmse": 1802.7658611145264,
        "mae": 1761.31298828125,
        "mape": 76.39307403564453,
        "directional_accuracy": 44.537815126050425,
        "delta_mse": 1111195.5,
        "delta_rmse": 340.31269947139185,
        "delta_mae": 346.1510009765625,
        "delta_mape": 14.650909423828125,
        "delta_directional_accuracy": 0.0
      },
      {
        "label": "minus_index",
        "channels": [
          "price",
          "usd_inr",
          "revenue",
          "profit"
        ],
        "removed_channel": "index",
        "mse": 748418.5625,
        "rmse": 865.1118786029932,
        "mae": 762.482421875,
        "mape": 33.83173370361328,
        "directional_accuracy": 44.957983193277315,
        "delta_mse": -1390350.6875,
        "delta_rmse": -597.3412830401413,
        "delta_mae": -652.6795654296875,
        "delta_mape": -27.910430908203125,
        "delta_directional_accuracy": 0.42016806722688926
      },
      {
        "label": "minus_usd_inr",
        "channels": [
          "price",
          "index",
          "revenue",
          "profit"
        ],
        "removed_channel": "usd_inr",
        "mse": 1625755.875,
        "rmse": 1275.0513224964711,
        "mae": 1243.070068359375,
        "mape": 54.14147186279297,
        "directional_accuracy": 45.18828451882845,
        "delta_mse": -513013.375,
        "delta_rmse": -187.4018391466634,
        "delta_mae": -172.0919189453125,
        "delta_mape": -7.6006927490234375,
        "delta_directional_accuracy": 0.6504693927780281
      },
      {
        "label": "minus_revenue",
        "channels": [
          "price",
          "index",
          "usd_inr",
          "profit"
        ],
        "removed_channel": "revenue",
        "mse": 361465.625,
        "rmse": 601.2201136023311,
        "mae": 560.4747924804688,
        "mape": 24.48180389404297,
        "directional_accuracy": 44.537815126050425,
        "delta_mse": -1777303.625,
        "delta_rmse": -861.2330480408034,
        "delta_mae": -854.6871948242188,
        "delta_mape": -37.26036071777344,
        "delta_directional_accuracy": 0.0
      },
      {
        "label": "minus_profit",
        "channels": [
          "price",
          "index",
          "usd_inr",
          "revenue"
        ],
        "removed_channel": "profit",
        "mse": 1279472.375,
        "rmse": 1131.137646354324,
        "mae": 1069.3145751953125,
        "mape": 47.06672286987305,
        "directional_accuracy": 44.537815126050425,
        "delta_mse": -859296.875,
        "delta_rmse": -331.3155152888105,
        "delta_mae": -345.847412109375,
        "delta_mape": -14.67544174194336,
        "delta_directional_accuracy": 0.0
      }
    ]
  },
  {
    "stock_id": "HAL",
    "mode": "per_stock",
    "generated_at": "2026-03-27T15:45:32.008712Z",
    "report_path": "/app/backend/models/model_store/feature_ablation/HAL_per_stock_feature_ablation_report.json",
    "configured_channels": [
      "price",
      "index",
      "usd_inr",
      "revenue",
      "profit"
    ],
    "transform_name": "stft",
    "entries": [
      {
        "label": "baseline",
        "channels": [
          "price",
          "index",
          "usd_inr",
          "revenue",
          "profit"
        ],
        "removed_channel": null,
        "mse": 1558056.0,
        "rmse": 1248.221134254664,
        "mae": 991.6810913085938,
        "mape": 23.1353759765625,
        "directional_accuracy": 49.583333333333336,
        "delta_mse": null,
        "delta_rmse": null,
        "delta_mae": null,
        "delta_mape": null,
        "delta_directional_accuracy": null
      },
      {
        "label": "minus_price",
        "channels": [
          "index",
          "usd_inr",
          "revenue",
          "profit"
        ],
        "removed_channel": "price",
        "mse": 414359.0625,
        "rmse": 643.7072801359326,
        "mae": 560.791748046875,
        "mape": 12.526191711425781,
        "directional_accuracy": 47.91666666666667,
        "delta_mse": -1143696.9375,
        "delta_rmse": -604.5138541187315,
        "delta_mae": -430.88934326171875,
        "delta_mape": -10.609184265136719,
        "delta_directional_accuracy": -1.6666666666666643
      },
      {
        "label": "minus_index",
        "channels": [
          "price",
          "usd_inr",
          "revenue",
          "profit"
        ],
        "removed_channel": "index",
        "mse": 4913860.5,
        "rmse": 2216.7229190857392,
        "mae": 2035.3258056640625,
        "mape": 45.87803649902344,
        "directional_accuracy": 44.166666666666664,
        "delta_mse": 3355804.5,
        "delta_rmse": 968.5017848310752,
        "delta_mae": 1043.6447143554688,
        "delta_mape": 22.742660522460938,
        "delta_directional_accuracy": -5.416666666666671
      },
      {
        "label": "minus_usd_inr",
        "channels": [
          "price",
          "index",
          "revenue",
          "profit"
        ],
        "removed_channel": "usd_inr",
        "mse": 894168.25,
        "rmse": 945.6047007074362,
        "mae": 743.6939697265625,
        "mape": 16.70675277709961,
        "directional_accuracy": 54.166666666666664,
        "delta_mse": -663887.75,
        "delta_rmse": -302.61643354722787,
        "delta_mae": -247.98712158203125,
        "delta_mape": -6.428623199462891,
        "delta_directional_accuracy": 4.583333333333329
      },
      {
        "label": "minus_revenue",
        "channels": [
          "price",
          "index",
          "usd_inr",
          "profit"
        ],
        "removed_channel": "revenue",
        "mse": 2883228.25,
        "rmse": 1698.0071407388132,
        "mae": 1498.9771728515625,
        "mape": 34.15772247314453,
        "directional_accuracy": 45.0,
        "delta_mse": 1325172.25,
        "delta_rmse": 449.7860064841491,
        "delta_mae": 507.29608154296875,
        "delta_mape": 11.022346496582031,
        "delta_directional_accuracy": -4.583333333333336
      },
      {
        "label": "minus_profit",
        "channels": [
          "price",
          "index",
          "usd_inr",
          "revenue"
        ],
        "removed_channel": "profit",
        "mse": 549931.1875,
        "rmse": 741.5734538803287,
        "mae": 658.1025390625,
        "mape": 14.972217559814453,
        "directional_accuracy": 45.416666666666664,
        "delta_mse": -1008124.8125,
        "delta_rmse": -506.64768037433544,
        "delta_mae": -333.57855224609375,
        "delta_mape": -8.163158416748047,
        "delta_directional_accuracy": -4.166666666666671
      }
    ]
  },
  {
    "stock_id": "HAL",
    "mode": "unified_with_embeddings",
    "generated_at": "2026-03-27T16:49:54.667046Z",
    "report_path": "/app/backend/models/model_store/feature_ablation/HAL_unified_with_embeddings_feature_ablation_report.json",
    "configured_channels": [
      "price",
      "index",
      "usd_inr",
      "revenue",
      "profit"
    ],
    "transform_name": "stft",
    "entries": [
      {
        "label": "baseline",
        "channels": [
          "price",
          "index",
          "usd_inr",
          "revenue",
          "profit"
        ],
        "removed_channel": null,
        "mse": 284430.0625,
        "rmse": 533.3198500899812,
        "mae": 404.2413330078125,
        "mape": 8.775927543640137,
        "directional_accuracy": 48.95397489539749,
        "delta_mse": null,
        "delta_rmse": null,
        "delta_mae": null,
        "delta_mape": null,
        "delta_directional_accuracy": null
      },
      {
        "label": "minus_price",
        "channels": [
          "index",
          "usd_inr",
          "revenue",
          "profit"
        ],
        "removed_channel": "price",
        "mse": 269817.75,
        "rmse": 519.4398425226929,
        "mae": 385.9070739746094,
        "mape": 8.27857780456543,
        "directional_accuracy": 57.74058577405857,
        "delta_mse": -14612.3125,
        "delta_rmse": -13.880007567288317,
        "delta_mae": -18.334259033203125,
        "delta_mape": -0.49734973907470703,
        "delta_directional_accuracy": 8.786610878661087
      },
      {
        "label": "minus_index",
        "channels": [
          "price",
          "usd_inr",
          "revenue",
          "profit"
        ],
        "removed_channel": "index",
        "mse": 307411.6875,
        "rmse": 554.4471909027947,
        "mae": 477.2841796875,
        "mape": 10.543034553527832,
        "directional_accuracy": 48.11715481171548,
        "delta_mse": 22981.625,
        "delta_rmse": 21.127340812813486,
        "delta_mae": 73.0428466796875,
        "delta_mape": 1.7671070098876953,
        "delta_directional_accuracy": -0.8368200836820066
      },
      {
        "label": "minus_usd_inr",
        "channels": [
          "price",
          "index",
          "revenue",
          "profit"
        ],
        "removed_channel": "usd_inr",
        "mse": 282260.40625,
        "rmse": 531.2818519863068,
        "mae": 425.5840759277344,
        "mape": 9.495766639709473,
        "directional_accuracy": 51.46443514644351,
        "delta_mse": -2169.65625,
        "delta_rmse": -2.03799810367434,
        "delta_mae": 21.342742919921875,
        "delta_mape": 0.7198390960693359,
        "delta_directional_accuracy": 2.5104602510460268
      },
      {
        "label": "minus_revenue",
        "channels": [
          "price",
          "index",
          "usd_inr",
          "profit"
        ],
        "removed_channel": "revenue",
        "mse": 195032.5,
        "rmse": 441.624840786838,
        "mae": 365.9378967285156,
        "mape": 8.004976272583008,
        "directional_accuracy": 58.995815899581594,
        "delta_mse": -89397.5625,
        "delta_rmse": -91.6950093031432,
        "delta_mae": -38.303436279296875,
        "delta_mape": -0.7709512710571289,
        "delta_directional_accuracy": 10.041841004184107
      },
      {
        "label": "minus_profit",
        "channels": [
          "price",
          "index",
          "usd_inr",
          "revenue"
        ],
        "removed_channel": "profit",
        "mse": 546323.875,
        "rmse": 739.1372504481153,
        "mae": 589.3709106445312,
        "mape": 12.824810028076172,
        "directional_accuracy": 53.55648535564853,
        "delta_mse": 261893.8125,
        "delta_rmse": 205.81740035813414,
        "delta_mae": 185.12957763671875,
        "delta_mape": 4.048882484436035,
        "delta_directional_accuracy": 4.602510460251047
      }
    ]
  },
  {
    "stock_id": "LT",
    "mode": "per_stock",
    "generated_at": "2026-03-27T15:24:41.957009Z",
    "report_path": "/app/backend/models/model_store/feature_ablation/LT_per_stock_feature_ablation_report.json",
    "configured_channels": [
      "price",
      "index",
      "usd_inr",
      "revenue",
      "profit"
    ],
    "transform_name": "stft",
    "entries": [
      {
        "label": "baseline",
        "channels": [
          "price",
          "index",
          "usd_inr",
          "revenue",
          "profit"
        ],
        "removed_channel": null,
        "mse": 52569.515625,
        "rmse": 229.2804300959853,
        "mae": 182.0734405517578,
        "mape": 4.852015018463135,
        "directional_accuracy": 51.24999999999999,
        "delta_mse": null,
        "delta_rmse": null,
        "delta_mae": null,
        "delta_mape": null,
        "delta_directional_accuracy": null
      },
      {
        "label": "minus_price",
        "channels": [
          "index",
          "usd_inr",
          "revenue",
          "profit"
        ],
        "removed_channel": "price",
        "mse": 500434.125,
        "rmse": 707.4136873145727,
        "mae": 589.3112182617188,
        "mape": 15.884380340576172,
        "directional_accuracy": 57.49999999999999,
        "delta_mse": 447864.609375,
        "delta_rmse": 478.1332572185874,
        "delta_mae": 407.23777770996094,
        "delta_mape": 11.032365322113037,
        "delta_directional_accuracy": 6.25
      },
      {
        "label": "minus_index",
        "channels": [
          "price",
          "usd_inr",
          "revenue",
          "profit"
        ],
        "removed_channel": "index",
        "mse": 128447.6328125,
        "rmse": 358.395916288816,
        "mae": 280.7565612792969,
        "mape": 7.550131320953369,
        "directional_accuracy": 55.41666666666667,
        "delta_mse": 75878.1171875,
        "delta_rmse": 129.1154861928307,
        "delta_mae": 98.68312072753906,
        "delta_mape": 2.6981163024902344,
        "delta_directional_accuracy": 4.1666666666666785
      },
      {
        "label": "minus_usd_inr",
        "channels": [
          "price",
          "index",
          "revenue",
          "profit"
        ],
        "removed_channel": "usd_inr",
        "mse": 94272.9921875,
        "rmse": 307.03907273749377,
        "mae": 249.11795043945312,
        "mape": 6.477700710296631,
        "directional_accuracy": 47.5,
        "delta_mse": 41703.4765625,
        "delta_rmse": 77.75864264150846,
        "delta_mae": 67.04450988769531,
        "delta_mape": 1.625685691833496,
        "delta_directional_accuracy": -3.749999999999993
      },
      {
        "label": "minus_revenue",
        "channels": [
          "price",
          "index",
          "usd_inr",
          "profit"
        ],
        "removed_channel": "revenue",
        "mse": 170603.9375,
        "rmse": 413.0422950497927,
        "mae": 304.4671936035156,
        "mape": 8.191802024841309,
        "directional_accuracy": 52.916666666666664,
        "delta_mse": 118034.421875,
        "delta_rmse": 183.7618649538074,
        "delta_mae": 122.39375305175781,
        "delta_mape": 3.339787006378174,
        "delta_directional_accuracy": 1.6666666666666714
      },
      {
        "label": "minus_profit",
        "channels": [
          "price",
          "index",
          "usd_inr",
          "revenue"
        ],
        "removed_channel": "profit",
        "mse": 386514.9375,
        "rmse": 621.7032551788675,
        "mae": 397.8074645996094,
        "mape": 10.656638145446777,
        "directional_accuracy": 54.166666666666664,
        "delta_mse": 333945.421875,
        "delta_rmse": 392.4228250828822,
        "delta_mae": 215.73402404785156,
        "delta_mape": 5.804623126983643,
        "delta_directional_accuracy": 2.9166666666666714
      }
    ]
  },
  {
    "stock_id": "LT",
    "mode": "unified_with_embeddings",
    "generated_at": "2026-03-27T16:49:54.666477Z",
    "report_path": "/app/backend/models/model_store/feature_ablation/LT_unified_with_embeddings_feature_ablation_report.json",
    "configured_channels": [
      "price",
      "index",
      "usd_inr",
      "revenue",
      "profit"
    ],
    "transform_name": "stft",
    "entries": [
      {
        "label": "baseline",
        "channels": [
          "price",
          "index",
          "usd_inr",
          "revenue",
          "profit"
        ],
        "removed_channel": null,
        "mse": 178470.1875,
        "rmse": 422.45732032952156,
        "mae": 380.08526611328125,
        "mape": 10.26545238494873,
        "directional_accuracy": 58.15899581589959,
        "delta_mse": null,
        "delta_rmse": null,
        "delta_mae": null,
        "delta_mape": null,
        "delta_directional_accuracy": null
      },
      {
        "label": "minus_price",
        "channels": [
          "index",
          "usd_inr",
          "revenue",
          "profit"
        ],
        "removed_channel": "price",
        "mse": 100379.046875,
        "rmse": 316.82652489177735,
        "mae": 256.3207092285156,
        "mape": 7.049124717712402,
        "directional_accuracy": 57.74058577405857,
        "delta_mse": -78091.140625,
        "delta_rmse": -105.63079543774421,
        "delta_mae": -123.76455688476562,
        "delta_mape": -3.216327667236328,
        "delta_directional_accuracy": -0.41841004184101394
      },
      {
        "label": "minus_index",
        "channels": [
          "price",
          "usd_inr",
          "revenue",
          "profit"
        ],
        "removed_channel": "index",
        "mse": 125628.3203125,
        "rmse": 354.44085587372683,
        "mae": 211.53369140625,
        "mape": 5.842714309692383,
        "directional_accuracy": 56.903765690376574,
        "delta_mse": -52841.8671875,
        "delta_rmse": -68.01646445579473,
        "delta_mae": -168.55157470703125,
        "delta_mape": -4.422738075256348,
        "delta_directional_accuracy": -1.2552301255230134
      },
      {
        "label": "minus_usd_inr",
        "channels": [
          "price",
          "index",
          "revenue",
          "profit"
        ],
        "removed_channel": "usd_inr",
        "mse": 118024.1015625,
        "rmse": 343.54636013571735,
        "mae": 275.5292053222656,
        "mape": 7.424957275390625,
        "directional_accuracy": 57.74058577405857,
        "delta_mse": -60446.0859375,
        "delta_rmse": -78.91096019380421,
        "delta_mae": -104.55606079101562,
        "delta_mape": -2.8404951095581055,
        "delta_directional_accuracy": -0.41841004184101394
      },
      {
        "label": "minus_revenue",
        "channels": [
          "price",
          "index",
          "usd_inr",
          "profit"
        ],
        "removed_channel": "revenue",
        "mse": 72935.3984375,
        "rmse": 270.0655447062805,
        "mae": 226.69854736328125,
        "mape": 6.102387428283691,
        "directional_accuracy": 48.53556485355649,
        "delta_mse": -105534.7890625,
        "delta_rmse": -152.39177562324107,
        "delta_mae": -153.38671875,
        "delta_mape": -4.163064956665039,
        "delta_directional_accuracy": -9.6234309623431
      },
      {
        "label": "minus_profit",
        "channels": [
          "price",
          "index",
          "usd_inr",
          "revenue"
        ],
        "removed_channel": "profit",
        "mse": 78486.15625,
        "rmse": 280.15380820185186,
        "mae": 233.98892211914062,
        "mape": 6.392301082611084,
        "directional_accuracy": 57.74058577405857,
        "delta_mse": -99984.03125,
        "delta_rmse": -142.3035121276697,
        "delta_mae": -146.09634399414062,
        "delta_mape": -3.8731513023376465,
        "delta_directional_accuracy": -0.41841004184101394
      }
    ]
  },
  {
    "stock_id": "RECLTD",
    "mode": "per_stock",
    "generated_at": "2026-03-27T15:55:52.056336Z",
    "report_path": "/app/backend/models/model_store/feature_ablation/RECLTD_per_stock_feature_ablation_report.json",
    "configured_channels": [
      "price",
      "index",
      "usd_inr",
      "revenue",
      "profit"
    ],
    "transform_name": "stft",
    "entries": [
      {
        "label": "baseline",
        "channels": [
          "price",
          "index",
          "usd_inr",
          "revenue",
          "profit"
        ],
        "removed_channel": null,
        "mse": 8167.5390625,
        "rmse": 90.3744381033708,
        "mae": 84.8618392944336,
        "mape": 23.077608108520508,
        "directional_accuracy": 43.75,
        "delta_mse": null,
        "delta_rmse": null,
        "delta_mae": null,
        "delta_mape": null,
        "delta_directional_accuracy": null
      },
      {
        "label": "minus_price",
        "channels": [
          "index",
          "usd_inr",
          "revenue",
          "profit"
        ],
        "removed_channel": "price",
        "mse": 16785.630859375,
        "rmse": 129.55937194728523,
        "mae": 119.76378631591797,
        "mape": 32.41633605957031,
        "directional_accuracy": 40.833333333333336,
        "delta_mse": 8618.091796875,
        "delta_rmse": 39.18493384391442,
        "delta_mae": 34.901947021484375,
        "delta_mape": 9.338727951049805,
        "delta_directional_accuracy": -2.9166666666666643
      },
      {
        "label": "minus_index",
        "channels": [
          "price",
          "usd_inr",
          "revenue",
          "profit"
        ],
        "removed_channel": "index",
        "mse": 9387.1728515625,
        "rmse": 96.88742359853781,
        "mae": 84.32073211669922,
        "mape": 23.283309936523438,
        "directional_accuracy": 44.583333333333336,
        "delta_mse": 1219.6337890625,
        "delta_rmse": 6.512985495167001,
        "delta_mae": -0.541107177734375,
        "delta_mape": 0.2057018280029297,
        "delta_directional_accuracy": 0.8333333333333357
      },
      {
        "label": "minus_usd_inr",
        "channels": [
          "price",
          "index",
          "revenue",
          "profit"
        ],
        "removed_channel": "usd_inr",
        "mse": 40077.6953125,
        "rmse": 200.1941440514682,
        "mae": 171.4176483154297,
        "mape": 47.31591796875,
        "directional_accuracy": 46.666666666666664,
        "delta_mse": 31910.15625,
        "delta_rmse": 109.81970594809738,
        "delta_mae": 86.5558090209961,
        "delta_mape": 24.238309860229492,
        "delta_directional_accuracy": 2.9166666666666643
      },
      {
        "label": "minus_revenue",
        "channels": [
          "price",
          "index",
          "usd_inr",
          "profit"
        ],
        "removed_channel": "revenue",
        "mse": 19759.814453125,
        "rmse": 140.56960714580163,
        "mae": 129.9522247314453,
        "mape": 35.49032211303711,
        "directional_accuracy": 43.75,
        "delta_mse": 11592.275390625,
        "delta_rmse": 50.19516904243082,
        "delta_mae": 45.09038543701172,
        "delta_mape": 12.412714004516602,
        "delta_directional_accuracy": 0.0
      },
      {
        "label": "minus_profit",
        "channels": [
          "price",
          "index",
          "usd_inr",
          "revenue"
        ],
        "removed_channel": "profit",
        "mse": 11298.333984375,
        "rmse": 106.29362156016231,
        "mae": 101.24663543701172,
        "mape": 27.471790313720703,
        "directional_accuracy": 40.833333333333336,
        "delta_mse": 3130.794921875,
        "delta_rmse": 15.919183456791501,
        "delta_mae": 16.384796142578125,
        "delta_mape": 4.394182205200195,
        "delta_directional_accuracy": -2.9166666666666643
      }
    ]
  },
  {
    "stock_id": "RECLTD",
    "mode": "unified_with_embeddings",
    "generated_at": "2026-03-27T16:49:54.667402Z",
    "report_path": "/app/backend/models/model_store/feature_ablation/RECLTD_unified_with_embeddings_feature_ablation_report.json",
    "configured_channels": [
      "price",
      "index",
      "usd_inr",
      "revenue",
      "profit"
    ],
    "transform_name": "stft",
    "entries": [
      {
        "label": "baseline",
        "channels": [
          "price",
          "index",
          "usd_inr",
          "revenue",
          "profit"
        ],
        "removed_channel": null,
        "mse": 13916.087890625,
        "rmse": 117.96646934881538,
        "mae": 109.58589172363281,
        "mape": 29.837772369384766,
        "directional_accuracy": 42.25941422594142,
        "delta_mse": null,
        "delta_rmse": null,
        "delta_mae": null,
        "delta_mape": null,
        "delta_directional_accuracy": null
      },
      {
        "label": "minus_price",
        "channels": [
          "index",
          "usd_inr",
          "revenue",
          "profit"
        ],
        "removed_channel": "price",
        "mse": 8582.37890625,
        "rmse": 92.64112966846852,
        "mae": 88.36514282226562,
        "mape": 23.849729537963867,
        "directional_accuracy": 43.51464435146444,
        "delta_mse": -5333.708984375,
        "delta_rmse": -25.325339680346858,
        "delta_mae": -21.220748901367188,
        "delta_mape": -5.988042831420898,
        "delta_directional_accuracy": 1.2552301255230205
      },
      {
        "label": "minus_index",
        "channels": [
          "price",
          "usd_inr",
          "revenue",
          "profit"
        ],
        "removed_channel": "index",
        "mse": 13283.9375,
        "rmse": 115.25596513846908,
        "mae": 94.56237030029297,
        "mape": 25.3177433013916,
        "directional_accuracy": 46.86192468619247,
        "delta_mse": -632.150390625,
        "delta_rmse": -2.7105042103463006,
        "delta_mae": -15.023521423339844,
        "delta_mape": -4.520029067993164,
        "delta_directional_accuracy": 4.602510460251047
      },
      {
        "label": "minus_usd_inr",
        "channels": [
          "price",
          "index",
          "revenue",
          "profit"
        ],
        "removed_channel": "usd_inr",
        "mse": 16827.33203125,
        "rmse": 129.72020671911528,
        "mae": 113.06938171386719,
        "mape": 30.87758445739746,
        "directional_accuracy": 42.083333333333336,
        "delta_mse": 2911.244140625,
        "delta_rmse": 11.753737370299902,
        "delta_mae": 3.483489990234375,
        "delta_mape": 1.0398120880126953,
        "delta_directional_accuracy": -0.17608089260808413
      },
      {
        "label": "minus_revenue",
        "channels": [
          "price",
          "index",
          "usd_inr",
          "profit"
        ],
        "removed_channel": "revenue",
        "mse": 7174.68310546875,
        "rmse": 84.70350114055941,
        "mae": 72.79066467285156,
        "mape": 19.40030860900879,
        "directional_accuracy": 45.18828451882845,
        "delta_mse": -6741.40478515625,
        "delta_rmse": -33.26296820825597,
        "delta_mae": -36.79522705078125,
        "delta_mape": -10.437463760375977,
        "delta_directional_accuracy": 2.9288702928870336
      },
      {
        "label": "minus_profit",
        "channels": [
          "price",
          "index",
          "usd_inr",
          "revenue"
        ],
        "removed_channel": "profit",
        "mse": 21792.287109375,
        "rmse": 147.62210914824038,
        "mae": 139.55157470703125,
        "mape": 37.99099349975586,
        "directional_accuracy": 41.00418410041841,
        "delta_mse": 7876.19921875,
        "delta_rmse": 29.655639799425003,
        "delta_mae": 29.965682983398438,
        "delta_mape": 8.153221130371094,
        "delta_directional_accuracy": -1.2552301255230063
      }
    ]
  },
  {
    "stock_id": "RELIANCE",
    "mode": "per_stock",
    "generated_at": "2026-03-27T15:14:18.849226Z",
    "report_path": "/app/backend/models/model_store/feature_ablation/RELIANCE_per_stock_feature_ablation_report.json",
    "configured_channels": [
      "price",
      "index",
      "usd_inr",
      "revenue",
      "profit"
    ],
    "transform_name": "stft",
    "entries": [
      {
        "label": "baseline",
        "channels": [
          "price",
          "index",
          "usd_inr",
          "revenue",
          "profit"
        ],
        "removed_channel": null,
        "mse": 23430.470703125,
        "rmse": 153.07014961489062,
        "mae": 124.71316528320312,
        "mape": 8.8572416305542,
        "directional_accuracy": 53.75,
        "delta_mse": null,
        "delta_rmse": null,
        "delta_mae": null,
        "delta_mape": null,
        "delta_directional_accuracy": null
      },
      {
        "label": "minus_price",
        "channels": [
          "index",
          "usd_inr",
          "revenue",
          "profit"
        ],
        "removed_channel": "price",
        "mse": 67900.3359375,
        "rmse": 260.5769290200113,
        "mae": 248.34326171875,
        "mape": 17.08020782470703,
        "directional_accuracy": 46.25,
        "delta_mse": 44469.865234375,
        "delta_rmse": 107.50677940512065,
        "delta_mae": 123.63009643554688,
        "delta_mape": 8.222966194152832,
        "delta_directional_accuracy": -7.5
      },
      {
        "label": "minus_index",
        "channels": [
          "price",
          "usd_inr",
          "revenue",
          "profit"
        ],
        "removed_channel": "index",
        "mse": 10522.8916015625,
        "rmse": 102.5811464235144,
        "mae": 86.43022155761719,
        "mape": 6.004271507263184,
        "directional_accuracy": 45.416666666666664,
        "delta_mse": -12907.5791015625,
        "delta_rmse": -50.48900319137623,
        "delta_mae": -38.28294372558594,
        "delta_mape": -2.8529701232910156,
        "delta_directional_accuracy": -8.333333333333336
      },
      {
        "label": "minus_usd_inr",
        "channels": [
          "price",
          "index",
          "revenue",
          "profit"
        ],
        "removed_channel": "usd_inr",
        "mse": 17066.681640625,
        "rmse": 130.63951025866945,
        "mae": 108.2351303100586,
        "mape": 7.485379219055176,
        "directional_accuracy": 44.166666666666664,
        "delta_mse": -6363.7890625,
        "delta_rmse": -22.430639356221178,
        "delta_mae": -16.47803497314453,
        "delta_mape": -1.3718624114990234,
        "delta_directional_accuracy": -9.583333333333336
      },
      {
        "label": "minus_revenue",
        "channels": [
          "price",
          "index",
          "usd_inr",
          "profit"
        ],
        "removed_channel": "revenue",
        "mse": 15527.19921875,
        "rmse": 124.60818279210238,
        "mae": 100.60176086425781,
        "mape": 7.182921409606934,
        "directional_accuracy": 54.58333333333333,
        "delta_mse": -7903.271484375,
        "delta_rmse": -28.46196682278824,
        "delta_mae": -24.111404418945312,
        "delta_mape": -1.6743202209472656,
        "delta_directional_accuracy": 0.8333333333333286
      },
      {
        "label": "minus_profit",
        "channels": [
          "price",
          "index",
          "usd_inr",
          "revenue"
        ],
        "removed_channel": "profit",
        "mse": 34758.76171875,
        "rmse": 186.4370181019585,
        "mae": 165.45843505859375,
        "mape": 11.693037986755371,
        "directional_accuracy": 53.333333333333336,
        "delta_mse": 11328.291015625,
        "delta_rmse": 33.366868487067876,
        "delta_mae": 40.745269775390625,
        "delta_mape": 2.835796356201172,
        "delta_directional_accuracy": -0.4166666666666643
      }
    ]
  },
  {
    "stock_id": "RELIANCE",
    "mode": "unified_with_embeddings",
    "generated_at": "2026-03-27T16:49:54.665991Z",
    "report_path": "/app/backend/models/model_store/feature_ablation/RELIANCE_unified_with_embeddings_feature_ablation_report.json",
    "configured_channels": [
      "price",
      "index",
      "usd_inr",
      "revenue",
      "profit"
    ],
    "transform_name": "stft",
    "entries": [
      {
        "label": "baseline",
        "channels": [
          "price",
          "index",
          "usd_inr",
          "revenue",
          "profit"
        ],
        "removed_channel": null,
        "mse": 6641.060546875,
        "rmse": 81.49270241484817,
        "mae": 67.8553695678711,
        "mape": 4.788622856140137,
        "directional_accuracy": 46.86192468619247,
        "delta_mse": null,
        "delta_rmse": null,
        "delta_mae": null,
        "delta_mape": null,
        "delta_directional_accuracy": null
      },
      {
        "label": "minus_price",
        "channels": [
          "index",
          "usd_inr",
          "revenue",
          "profit"
        ],
        "removed_channel": "price",
        "mse": 13504.244140625,
        "rmse": 116.20776282428382,
        "mae": 98.60685729980469,
        "mape": 7.011826992034912,
        "directional_accuracy": 53.13807531380753,
        "delta_mse": 6863.18359375,
        "delta_rmse": 34.71506040943565,
        "delta_mae": 30.751487731933594,
        "delta_mape": 2.2232041358947754,
        "delta_directional_accuracy": 6.276150627615067
      },
      {
        "label": "minus_index",
        "channels": [
          "price",
          "usd_inr",
          "revenue",
          "profit"
        ],
        "removed_channel": "index",
        "mse": 17846.771484375,
        "rmse": 133.59180919642864,
        "mae": 114.54981231689453,
        "mape": 7.851192474365234,
        "directional_accuracy": 45.60669456066946,
        "delta_mse": 11205.7109375,
        "delta_rmse": 52.099106781580474,
        "delta_mae": 46.69444274902344,
        "delta_mape": 3.0625696182250977,
        "delta_directional_accuracy": -1.2552301255230063
      },
      {
        "label": "minus_usd_inr",
        "channels": [
          "price",
          "index",
          "revenue",
          "profit"
        ],
        "removed_channel": "usd_inr",
        "mse": 8150.33740234375,
        "rmse": 90.27921910574852,
        "mae": 77.84815979003906,
        "mape": 5.44460916519165,
        "directional_accuracy": 47.083333333333336,
        "delta_mse": 1509.27685546875,
        "delta_rmse": 8.786516690900356,
        "delta_mae": 9.992790222167969,
        "delta_mape": 0.6559863090515137,
        "delta_directional_accuracy": 0.22140864714086916
      },
      {
        "label": "minus_revenue",
        "channels": [
          "price",
          "index",
          "usd_inr",
          "profit"
        ],
        "removed_channel": "revenue",
        "mse": 8125.05029296875,
        "rmse": 90.13906086136437,
        "mae": 74.35015106201172,
        "mape": 5.167962551116943,
        "directional_accuracy": 46.44351464435147,
        "delta_mse": 1483.98974609375,
        "delta_rmse": 8.646358446516203,
        "delta_mae": 6.494781494140625,
        "delta_mape": 0.37933969497680664,
        "delta_directional_accuracy": -0.4184100418409997
      },
      {
        "label": "minus_profit",
        "channels": [
          "price",
          "index",
          "usd_inr",
          "revenue"
        ],
        "removed_channel": "profit",
        "mse": 6974.806640625,
        "rmse": 83.51530782212923,
        "mae": 71.1340103149414,
        "mape": 5.016631603240967,
        "directional_accuracy": 48.95397489539749,
        "delta_mse": 333.74609375,
        "delta_rmse": 2.0226054072810626,
        "delta_mae": 3.2786407470703125,
        "delta_mape": 0.22800874710083008,
        "delta_directional_accuracy": 2.09205020920502
      }
    ]
  }
]